sphere_n/__init__.py
sphere_n/cylind_n.py
sphere_n/discrep_2.py
sphere_n/sphere_n.py
sphere_n-0.4.dist-info/licenses/LICENSE.txt
sphere_n-0.4.dist-info/METADATA
sphere_n-0.4.dist-info/WHEEL
sphere_n-0.4.dist-info/top_level.txt
sphere_n-0.4.dist-info/RECORD
