Metadata-Version: 2.4
Name: sphere-n
Version: 0.4
Summary: A library for low-discrepancy sequences
Home-page: https://github.com/pyscaffold/pyscaffold/
Author: Wai-Shing Luk
Author-email: luk036@gmail.com
License: MIT
Project-URL: Documentation, https://pyscaffold.org/
Platform: any
Classifier: Development Status :: 4 - Beta
Classifier: Programming Language :: Python
Requires-Python: >=3.10
License-File: LICENSE.txt
Requires-Dist: importlib-metadata
Requires-Dist: numpy
Requires-Dist: lds-gen
Provides-Extra: testing
Requires-Dist: setuptools; extra == "testing"
Requires-Dist: pytest; extra == "testing"
Requires-Dist: pytest-cov; extra == "testing"
Requires-Dist: lds-gen; extra == "testing"
Requires-Dist: numpy; extra == "testing"
Requires-Dist: scipy; extra == "testing"
Dynamic: license-file
